expectpy
