Metadata-Version: 1.1
Name: expectpy
Version: 0.0.4
Summary: assertion library like chai.expect.
Home-page: https://github.com/float1251/expectpy
Author: takahiro iwatani
Author-email: taka.05022002@gmail.com
License: MIT
Platform: UNKNOWN
Classifier: Development Status :: 3 - Alpha
Classifier: License :: OSI Approved :: MIT License
